
{
  "Admins": [
    {
      "img": "",
      "name": "",
      "subject": "",
      "Mobile": "",
      "email": "",
      "username": "",
      "password": "",
      "id": 1
    },
    {
      "img": "",
      "name": "navven",
      "subject": "maths",
      "gender": "male",
      "age": "99",
      "mobile": "ssssssss",
      "email": "ssssssss",
      "username": "naveen123",
      "password": "123",
      "id": 8
    },
    {
      "img": "",
      "name": "",
      "subject": "",
      "gender": "",
      "age": "",
      "mobile": "",
      "email": "",
      "username": "",
      "password": "",
      "id": 9
    },
    {
      "img": "",
      "name": "",
      "subject": "",
      "gender": "",
      "age": "",
      "mobile": "",
      "email": "",
      "username": "",
      "password": "",
      "id": 10
    },
    {
      "img": "",
      "name": "",
      "subject": "",
      "gender": "",
      "age": "",
      "mobile": "",
      "email": "",
      "username": "",
      "password": "",
      "id": 11
    }
  ]
}